single_access
