Metadata-Version: 1.0
Name: single-access
Version: 0.0.2
Summary: Single access to run python script
Home-page: https://bitbucket.org/imbolc/single_access
Author: Imbolc
Author-email: imbolc@imbolc.name
License: ISC
Platform: UNKNOWN
Classifier: Development Status :: 4 - Beta
Classifier: Intended Audience :: Developers
Classifier: Natural Language :: English
Classifier: License :: OSI Approved :: ISC License (ISCL)
Classifier: Programming Language :: Python
